{
    "questions": [
      {
        "type": "matching_connection",
        "id": "014",
        "question": " Rank activity ",
        "pairs": [
          { "left": "Going Home", "right": "5" },
          { "left": "Training", "right": "3" },
          { "left": "Lunch", "right": "4" },
          { "left": "Assembly", "right": "2" },
          { "left": "Comming to school", "right": "1" }
        ],
        "user_response": ""
      },
      {
        "type": "matching_connection",
        "id": "014",
        "question": " Rank activity ",
        "pairs": [
          { "left": "un well", "right": "Sick room" },
          { "left": "sing", "right": "Music room" },
          { "left": "study and spent time", "right": "Class room" },
          { "left": "Teachers", "right": "Staff room" },
          { "left": "Comming to school", "right": "1" }
        ],
        "user_response": ""
      }
    ],
    "taxonomy": {
      "difficulty_levels": ["easy", "medium", "hard"],
      "subject_areas": ["science", "history", "geography", "computer-science"],
      "question_types": ["mcq", "fill_in_blank", "true_false", "matching", "short_answer", "multi_select", "ordering"]
    }
  }
  
